{
  "$schema": "https://schema.management.azure.com/schemas/2019-04-01/deploymentTemplate.json#",
  "languageVersion": "2.1-experimental",
  "contentVersion": "1.0.0.0",
  "metadata": {
    "_EXPERIMENTAL_WARNING": "This template uses ARM features that are experimental. Experimental features should be enabled for testing purposes only, as there are no guarantees about the quality or stability of these features. Do not enable these settings for any production usage, or your production environment may be subject to breaking.",
    "_EXPERIMENTAL_FEATURES_ENABLED": [
      "Enable wait and retry feature"
    ],
    "_generator": {
      "name": "bicep",
      "version": "0.41.2.15936",
      "templateHash": "1221750354809535923"
    }
  },
  "imports": {
    "graph": {
      "provider": "MicrosoftGraph",
      "version": "1.0.0"
    }
  },
  "resources": {
    "app": {
      "import": "graph",
      "type": "Microsoft.Graph/applications@v1.0",
      "properties": {
        "displayName": "shengloltestapp",
        "uniqueName": "shengloltestapp"
      }
    }
  }
}